[
 {
  "default_value": null,
  "doc_type": "Lead",
  "docstatus": 0,
  "doctype": "Property Setter",
  "doctype_or_field": "DocField",
  "field_name": "job_title",
  "is_system_generated": 0,
  "modified": "2024-07-23 11:11:39.399960",
  "module": null,
  "name": "Lead-job_title-hidden",
  "property": "hidden",
  "property_type": "Check",
  "row_name": null,
  "value": "1"
 },
 {
  "default_value": null,
  "doc_type": "Lead",
  "docstatus": 0,
  "doctype": "Property Setter",
  "doctype_or_field": "DocField",
  "field_name": "first_name",
  "is_system_generated": 0,
  "modified": "2024-07-23 11:17:40.750731",
  "module": null,
  "name": "Lead-first_name-fetch_from",
  "property": "fetch_from",
  "property_type": "Small Text",
  "row_name": null,
  "value": "custom_individual.first_name"
 },
 {
  "default_value": null,
  "doc_type": "Lead",
  "docstatus": 0,
  "doctype": "Property Setter",
  "doctype_or_field": "DocField",
  "field_name": "middle_name",
  "is_system_generated": 0,
  "modified": "2024-07-23 11:17:40.872110",
  "module": null,
  "name": "Lead-middle_name-fetch_from",
  "property": "fetch_from",
  "property_type": "Small Text",
  "row_name": null,
  "value": "custom_individual.middle_name"
 },
 {
  "default_value": null,
  "doc_type": "Lead",
  "docstatus": 0,
  "doctype": "Property Setter",
  "doctype_or_field": "DocField",
  "field_name": "last_name",
  "is_system_generated": 0,
  "modified": "2024-07-23 11:17:41.043776",
  "module": null,
  "name": "Lead-last_name-fetch_from",
  "property": "fetch_from",
  "property_type": "Small Text",
  "row_name": null,
  "value": "custom_individual.last_name"
 },
 {
  "default_value": null,
  "doc_type": "Lead",
  "docstatus": 0,
  "doctype": "Property Setter",
  "doctype_or_field": "DocField",
  "field_name": "salutation",
  "is_system_generated": 0,
  "modified": "2024-07-23 11:20:21.701543",
  "module": null,
  "name": "Lead-salutation-depends_on",
  "property": "depends_on",
  "property_type": "Data",
  "row_name": null,
  "value": "eval:doc.custom_customer_type == \"Individual\""
 },
 {
  "default_value": null,
  "doc_type": "Lead",
  "docstatus": 0,
  "doctype": "Property Setter",
  "doctype_or_field": "DocField",
  "field_name": "first_name",
  "is_system_generated": 0,
  "modified": "2024-07-23 11:20:21.887777",
  "module": null,
  "name": "Lead-first_name-depends_on",
  "property": "depends_on",
  "property_type": "Data",
  "row_name": null,
  "value": "eval:doc.custom_customer_type == \"Individual\""
 },
 {
  "default_value": null,
  "doc_type": "Lead",
  "docstatus": 0,
  "doctype": "Property Setter",
  "doctype_or_field": "DocField",
  "field_name": "contact_info_tab",
  "is_system_generated": 0,
  "modified": "2024-07-23 11:20:22.042381",
  "module": null,
  "name": "Lead-contact_info_tab-depends_on",
  "property": "depends_on",
  "property_type": "Data",
  "row_name": null,
  "value": "eval:doc.custom_customer_type == \"Individual\""
 },
 {
  "default_value": null,
  "doc_type": "Lead",
  "docstatus": 0,
  "doctype": "Property Setter",
  "doctype_or_field": "DocField",
  "field_name": "organization_section",
  "is_system_generated": 0,
  "modified": "2024-07-23 11:21:41.727071",
  "module": null,
  "name": "Lead-organization_section-depends_on",
  "property": "depends_on",
  "property_type": "Data",
  "row_name": null,
  "value": "eval:doc.custom_customer_type == \"Company\""
 },
 {
  "default_value": null,
  "doc_type": "Lead",
  "docstatus": 0,
  "doctype": "Property Setter",
  "doctype_or_field": "DocField",
  "field_name": "qualification_tab",
  "is_system_generated": 0,
  "modified": "2024-07-23 11:22:39.265266",
  "module": null,
  "name": "Lead-qualification_tab-hidden",
  "property": "hidden",
  "property_type": "Check",
  "row_name": null,
  "value": "1"
 },
 {
  "default_value": null,
  "doc_type": "Lead",
  "docstatus": 0,
  "doctype": "Property Setter",
  "doctype_or_field": "DocField",
  "field_name": "other_info_tab",
  "is_system_generated": 0,
  "modified": "2024-07-23 11:22:39.452789",
  "module": null,
  "name": "Lead-other_info_tab-hidden",
  "property": "hidden",
  "property_type": "Check",
  "row_name": null,
  "value": "1"
 },
 {
  "default_value": null,
  "doc_type": "Lead",
  "docstatus": 0,
  "doctype": "Property Setter",
  "doctype_or_field": "DocField",
  "field_name": "email_id",
  "is_system_generated": 0,
  "modified": "2024-07-23 11:26:53.222333",
  "module": null,
  "name": "Lead-email_id-fetch_from",
  "property": "fetch_from",
  "property_type": "Small Text",
  "row_name": null,
  "value": "custom_individual.custom_email"
 },
 {
  "default_value": null,
  "doc_type": "Lead",
  "docstatus": 0,
  "doctype": "Property Setter",
  "doctype_or_field": "DocField",
  "field_name": "mobile_no",
  "is_system_generated": 0,
  "modified": "2024-07-23 11:26:53.426555",
  "module": null,
  "name": "Lead-mobile_no-fetch_from",
  "property": "fetch_from",
  "property_type": "Small Text",
  "row_name": null,
  "value": "custom_individual.custom_mobile_number"
 },
 {
  "default_value": null,
  "doc_type": "Lead",
  "docstatus": 0,
  "doctype": "Property Setter",
  "doctype_or_field": "DocField",
  "field_name": "address_html",
  "is_system_generated": 0,
  "modified": "2024-08-16 12:18:49.135877",
  "module": null,
  "name": "Lead-address_html-hidden",
  "property": "hidden",
  "property_type": "Check",
  "row_name": null,
  "value": "1"
 },
 {
  "default_value": null,
  "doc_type": "Lead",
  "docstatus": 0,
  "doctype": "Property Setter",
  "doctype_or_field": "DocField",
  "field_name": "city",
  "is_system_generated": 0,
  "modified": "2024-08-16 12:18:49.338974",
  "module": null,
  "name": "Lead-city-hidden",
  "property": "hidden",
  "property_type": "Check",
  "row_name": null,
  "value": "1"
 },
 {
  "default_value": null,
  "doc_type": "Lead",
  "docstatus": 0,
  "doctype": "Property Setter",
  "doctype_or_field": "DocField",
  "field_name": "state",
  "is_system_generated": 0,
  "modified": "2024-08-16 12:18:49.470799",
  "module": null,
  "name": "Lead-state-hidden",
  "property": "hidden",
  "property_type": "Check",
  "row_name": null,
  "value": "1"
 },
 {
  "default_value": null,
  "doc_type": "Lead",
  "docstatus": 0,
  "doctype": "Property Setter",
  "doctype_or_field": "DocField",
  "field_name": "country",
  "is_system_generated": 0,
  "modified": "2024-08-16 12:18:49.593508",
  "module": null,
  "name": "Lead-country-hidden",
  "property": "hidden",
  "property_type": "Check",
  "row_name": null,
  "value": "1"
 },
 {
  "default_value": null,
  "doc_type": "Lead",
  "docstatus": 0,
  "doctype": "Property Setter",
  "doctype_or_field": "DocField",
  "field_name": "type",
  "is_system_generated": 0,
  "modified": "2024-08-16 12:19:44.581466",
  "module": null,
  "name": "Lead-type-hidden",
  "property": "hidden",
  "property_type": "Check",
  "row_name": null,
  "value": "1"
 },
 {
  "default_value": null,
  "doc_type": "Lead",
  "docstatus": 0,
  "doctype": "Property Setter",
  "doctype_or_field": "DocField",
  "field_name": "request_type",
  "is_system_generated": 0,
  "modified": "2024-08-16 12:19:44.783067",
  "module": null,
  "name": "Lead-request_type-hidden",
  "property": "hidden",
  "property_type": "Check",
  "row_name": null,
  "value": "1"
 },
 {
  "default_value": null,
  "doc_type": "Lead",
  "docstatus": 0,
  "doctype": "Property Setter",
  "doctype_or_field": "DocField",
  "field_name": "address_section",
  "is_system_generated": 0,
  "modified": "2024-08-16 12:21:11.028339",
  "module": null,
  "name": "Lead-address_section-hidden",
  "property": "hidden",
  "property_type": "Check",
  "row_name": null,
  "value": "1"
 },
 {
  "default_value": null,
  "doc_type": "Opportunity",
  "docstatus": 0,
  "doctype": "Property Setter",
  "doctype_or_field": "DocField",
  "field_name": "organization_details_section",
  "is_system_generated": 0,
  "modified": "2024-08-16 12:27:47.088726",
  "module": null,
  "name": "Opportunity-organization_details_section-hidden",
  "property": "hidden",
  "property_type": "Check",
  "row_name": null,
  "value": "1"
 },
 {
  "default_value": null,
  "doc_type": "Opportunity",
  "docstatus": 0,
  "doctype": "Property Setter",
  "doctype_or_field": "DocField",
  "field_name": "column_break_10",
  "is_system_generated": 0,
  "modified": "2024-08-30 12:02:33.764735",
  "module": null,
  "name": "Opportunity-column_break_10-default",
  "property": "default",
  "property_type": "Text",
  "row_name": null,
  "value": "1.In Discussion Meeting Pending"
 },
 {
  "default_value": null,
  "doc_type": "Lead",
  "docstatus": 0,
  "doctype": "Property Setter",
  "doctype_or_field": "DocField",
  "field_name": "no_of_employees",
  "is_system_generated": 0,
  "modified": "2024-08-30 12:41:43.520204",
  "module": null,
  "name": "Lead-no_of_employees-label",
  "property": "label",
  "property_type": "Data",
  "row_name": null,
  "value": "No of Employees (optional)"
 },
 {
  "default_value": null,
  "doc_type": "Lead",
  "docstatus": 0,
  "doctype": "Property Setter",
  "doctype_or_field": "DocField",
  "field_name": "annual_revenue",
  "is_system_generated": 0,
  "modified": "2024-08-30 12:41:43.678097",
  "module": null,
  "name": "Lead-annual_revenue-label",
  "property": "label",
  "property_type": "Data",
  "row_name": null,
  "value": "Annual Revenue (optional)"
 },
 {
  "default_value": null,
  "doc_type": "Lead",
  "docstatus": 0,
  "doctype": "Property Setter",
  "doctype_or_field": "DocField",
  "field_name": "fax",
  "is_system_generated": 0,
  "modified": "2024-08-30 12:41:43.864125",
  "module": null,
  "name": "Lead-fax-hidden",
  "property": "hidden",
  "property_type": "Check",
  "row_name": null,
  "value": "1"
 },
 {
  "default_value": null,
  "doc_type": "Lead",
  "docstatus": 0,
  "doctype": "Property Setter",
  "doctype_or_field": "DocField",
  "field_name": "market_segment",
  "is_system_generated": 0,
  "modified": "2024-08-30 12:41:44.048900",
  "module": null,
  "name": "Lead-market_segment-hidden",
  "property": "hidden",
  "property_type": "Check",
  "row_name": null,
  "value": "1"
 },
 {
  "default_value": null,
  "doc_type": "Lead",
  "docstatus": 0,
  "doctype": "Property Setter",
  "doctype_or_field": "DocField",
  "field_name": "column_break_31",
  "is_system_generated": 0,
  "modified": "2024-08-30 12:41:44.194057",
  "module": null,
  "name": "Lead-column_break_31-hidden",
  "property": "hidden",
  "property_type": "Check",
  "row_name": null,
  "value": "1"
 },
 {
  "default_value": null,
  "doc_type": "Customer",
  "docstatus": 0,
  "doctype": "Property Setter",
  "doctype_or_field": "DocField",
  "field_name": "naming_series",
  "is_system_generated": 0,
  "modified": "2025-09-19 18:02:08.080529",
  "module": null,
  "name": "Customer-naming_series-options",
  "property": "options",
  "property_type": "Text",
  "row_name": null,
  "value": "CUST-.YYYY.-"
 },
 {
  "default_value": null,
  "doc_type": "Customer",
  "docstatus": 0,
  "doctype": "Property Setter",
  "doctype_or_field": "DocField",
  "field_name": "naming_series",
  "is_system_generated": 0,
  "modified": "2025-09-19 18:02:08.266581",
  "module": null,
  "name": "Customer-naming_series-default",
  "property": "default",
  "property_type": "Text",
  "row_name": null,
  "value": "CUST-.YYYY.-"
 },
 {
  "default_value": null,
  "doc_type": "Customer",
  "docstatus": 0,
  "doctype": "Property Setter",
  "doctype_or_field": "DocField",
  "field_name": "naming_series",
  "is_system_generated": 0,
  "modified": "2025-12-29 15:59:24.708055",
  "module": null,
  "name": "Customer-naming_series-hidden",
  "property": "hidden",
  "property_type": "Check",
  "row_name": null,
  "value": "0"
 },
 {
  "default_value": null,
  "doc_type": "Customer",
  "docstatus": 0,
  "doctype": "Property Setter",
  "doctype_or_field": "DocField",
  "field_name": "naming_series",
  "is_system_generated": 0,
  "modified": "2025-12-29 15:59:25.555338",
  "module": null,
  "name": "Customer-naming_series-reqd",
  "property": "reqd",
  "property_type": "Check",
  "row_name": null,
  "value": "1"
 },
 {
  "default_value": null,
  "doc_type": "Quotation",
  "docstatus": 0,
  "doctype": "Property Setter",
  "doctype_or_field": "DocField",
  "field_name": "base_rounded_total",
  "is_system_generated": 0,
  "modified": "2025-12-31 16:57:55.535523",
  "module": null,
  "name": "Quotation-base_rounded_total-hidden",
  "property": "hidden",
  "property_type": "Check",
  "row_name": null,
  "value": "1"
 },
 {
  "default_value": null,
  "doc_type": "Quotation",
  "docstatus": 0,
  "doctype": "Property Setter",
  "doctype_or_field": "DocField",
  "field_name": "base_rounded_total",
  "is_system_generated": 0,
  "modified": "2025-12-31 16:57:56.384070",
  "module": null,
  "name": "Quotation-base_rounded_total-print_hide",
  "property": "print_hide",
  "property_type": "Check",
  "row_name": null,
  "value": "1"
 },
 {
  "default_value": null,
  "doc_type": "Quotation",
  "docstatus": 0,
  "doctype": "Property Setter",
  "doctype_or_field": "DocField",
  "field_name": "rounded_total",
  "is_system_generated": 0,
  "modified": "2025-12-31 16:57:56.436587",
  "module": null,
  "name": "Quotation-rounded_total-hidden",
  "property": "hidden",
  "property_type": "Check",
  "row_name": null,
  "value": "1"
 },
 {
  "default_value": null,
  "doc_type": "Quotation",
  "docstatus": 0,
  "doctype": "Property Setter",
  "doctype_or_field": "DocField",
  "field_name": "rounded_total",
  "is_system_generated": 0,
  "modified": "2025-12-31 16:57:56.491130",
  "module": null,
  "name": "Quotation-rounded_total-print_hide",
  "property": "print_hide",
  "property_type": "Check",
  "row_name": null,
  "value": "1"
 },
 {
  "default_value": null,
  "doc_type": "Quotation",
  "docstatus": 0,
  "doctype": "Property Setter",
  "doctype_or_field": "DocField",
  "field_name": "disable_rounded_total",
  "is_system_generated": 0,
  "modified": "2025-12-31 16:57:56.543811",
  "module": null,
  "name": "Quotation-disable_rounded_total-default",
  "property": "default",
  "property_type": "Text",
  "row_name": null,
  "value": "1"
 },
 {
  "default_value": null,
  "doc_type": "Quotation",
  "docstatus": 0,
  "doctype": "Property Setter",
  "doctype_or_field": "DocField",
  "field_name": "in_words",
  "is_system_generated": 0,
  "modified": "2025-12-31 16:57:58.831709",
  "module": null,
  "name": "Quotation-in_words-hidden",
  "property": "hidden",
  "property_type": "Check",
  "row_name": null,
  "value": "0"
 },
 {
  "default_value": null,
  "doc_type": "Quotation",
  "docstatus": 0,
  "doctype": "Property Setter",
  "doctype_or_field": "DocField",
  "field_name": "in_words",
  "is_system_generated": 0,
  "modified": "2025-12-31 16:57:58.886381",
  "module": null,
  "name": "Quotation-in_words-print_hide",
  "property": "print_hide",
  "property_type": "Check",
  "row_name": null,
  "value": "0"
 },
 {
  "default_value": null,
  "doc_type": "Lead",
  "docstatus": 0,
  "doctype": "Property Setter",
  "doctype_or_field": "DocType",
  "field_name": null,
  "is_system_generated": 0,
  "modified": "2026-01-12 10:57:10.424955",
  "module": null,
  "name": "Lead-main-field_order",
  "property": "field_order",
  "property_type": "Data",
  "row_name": null,
  "value": "[\"naming_series\", \"custom_customer_type\", \"custom_customer_group\", \"column_break_1\", \"job_title\", \"source\", \"custom_source_of_creation\", \"col_break123\", \"lead_owner\", \"status\", \"customer\", \"type\", \"request_type\", \"custom_product_section\", \"custom_item\", \"custom_item_name\", \"custom_column_break_47kf7\", \"custom_uom\", \"custom_individual_section\", \"custom_individual\", \"custom_section_break_mrekc\", \"salutation\", \"first_name\", \"middle_name\", \"last_name\", \"custom_column_break_t30lt\", \"lead_name\", \"gender\", \"contact_info_tab\", \"email_id\", \"website\", \"column_break_20\", \"mobile_no\", \"whatsapp_no\", \"column_break_16\", \"phone\", \"phone_ext\", \"organization_section\", \"company_name\", \"territory\", \"custom_hse_check\", \"column_break_28\", \"industry\", \"no_of_employees\", \"annual_revenue\", \"fax\", \"market_segment\", \"column_break_31\", \"custom_organization_documents\", \"custom_trade_license\", \"custom_trade_license_attachment\", \"custom_trade_license_expiry\", \"custom_column_break_hzivd\", \"custom_vat_certificate\", \"custom_vat_certificate_attachment\", \"custom_poc_section\", \"custom_poc\", \"address_section\", \"address_html\", \"column_break_38\", \"city\", \"state\", \"country\", \"column_break2\", \"contact_html\", \"qualification_tab\", \"qualification_status\", \"column_break_64\", \"qualified_by\", \"qualified_on\", \"other_info_tab\", \"campaign_name\", \"company\", \"column_break_22\", \"language\", \"image\", \"title\", \"column_break_50\", \"disabled\", \"unsubscribed\", \"blog_subscriber\", \"activities_tab\", \"open_activities_html\", \"all_activities_section\", \"all_activities_html\", \"notes_tab\", \"notes_html\", \"notes\", \"dashboard_tab\"]"
 },
 {
  "default_value": null,
  "doc_type": "Customer",
  "docstatus": 0,
  "doctype": "Property Setter",
  "doctype_or_field": "DocType",
  "field_name": null,
  "is_system_generated": 0,
  "modified": "2026-02-07 11:01:03.088471",
  "module": null,
  "name": "Customer-main-quick_entry",
  "property": "quick_entry",
  "property_type": "Check",
  "row_name": null,
  "value": "0"
 },
 {
  "default_value": null,
  "doc_type": "Quotation",
  "docstatus": 0,
  "doctype": "Property Setter",
  "doctype_or_field": "DocField",
  "field_name": "scan_barcode",
  "is_system_generated": 1,
  "modified": "2026-02-13 13:39:50.905436",
  "module": null,
  "name": "Quotation-scan_barcode-hidden",
  "property": "hidden",
  "property_type": "Check",
  "row_name": null,
  "value": "0"
 },
 {
  "default_value": null,
  "doc_type": "Opportunity",
  "docstatus": 0,
  "doctype": "Property Setter",
  "doctype_or_field": "DocField",
  "field_name": "address_contact_section",
  "is_system_generated": 0,
  "modified": "2026-06-04 14:59:35.275627",
  "module": null,
  "name": "Opportunity-address_contact_section-hidden",
  "property": "hidden",
  "property_type": "Check",
  "row_name": null,
  "value": "1"
 },
 {
  "default_value": null,
  "doc_type": "Opportunity",
  "docstatus": 0,
  "doctype": "Property Setter",
  "doctype_or_field": "DocType",
  "field_name": null,
  "is_system_generated": 0,
  "modified": "2026-06-16 12:00:00.000000",
  "module": null,
  "name": "Opportunity-main-field_order",
  "property": "field_order",
  "property_type": "Data",
  "row_name": null,
  "value": "[\"naming_series\", \"opportunity_from\", \"party_name\", \"customer_name\", \"status\", \"column_break0\", \"opportunity_type\", \"source\", \"opportunity_owner\", \"custom_opportunity_creation_date\", \"custom_contract_expiry\", \"custom_payment_terms\", \"custom_invoicing_frequency\", \"custom_invoicing_type\", \"column_break_10\", \"sales_stage\", \"expected_closing\", \"probability\", \"custom_activity_at_opportunity\", \"custom_activity\", \"custom_deal_type\", \"custom_pricing_model\", \"custom_finance_dossier_status\", \"custom_quotation_status\", \"organization_details_section\", \"no_of_employees\", \"annual_revenue\", \"customer_group\", \"column_break_23\", \"industry\", \"market_segment\", \"website\", \"column_break_31\", \"city\", \"state\", \"country\", \"territory\", \"section_break_14\", \"custom_product\", \"currency\", \"column_break_36\", \"custom_uom\", \"custom_rate\", \"conversion_rate\", \"column_break_17\", \"custom_expected_monthly_volume\", \"opportunity_amount\", \"base_opportunity_amount\", \"custom_contact_details\", \"custom_point_of_contact\", \"custom_hse_details\", \"custom_opportunity_hse\", \"more_info\", \"company\", \"campaign\", \"transaction_date\", \"column_break1\", \"language\", \"amended_from\", \"title\", \"first_response_time\", \"lost_detail_section\", \"lost_reasons\", \"order_lost_reason\", \"column_break_56\", \"competitors\", \"contact_info\", \"primary_contact_section\", \"contact_person\", \"job_title\", \"column_break_54\", \"contact_email\", \"contact_mobile\", \"column_break_22\", \"whatsapp\", \"phone\", \"phone_ext\", \"billing_address_section\", \"billing_address_html\", \"customer_billing_address\", \"billing_address_display\", \"address_contact_section\", \"address_html\", \"customer_address\", \"address_display\", \"column_break3\", \"contact_html\", \"contact_display\", \"items_section\", \"items\", \"section_break_32\", \"base_total\", \"column_break_33\", \"total\", \"activities_tab\", \"open_activities_html\", \"all_activities_section\", \"all_activities_html\", \"notes_tab\", \"notes_html\", \"notes\", \"dashboard_tab\"]"
 },
 {
  "default_value": null,
  "doc_type": "Quotation",
  "docstatus": 0,
  "doctype": "Property Setter",
  "doctype_or_field": "DocType",
  "field_name": null,
  "is_system_generated": 0,
  "modified": "2026-06-05 11:00:01.737390",
  "module": null,
  "name": "Quotation-main-field_order",
  "property": "field_order",
  "property_type": "Data",
  "row_name": null,
  "value": "[\"customer_section\", \"title\", \"naming_series\", \"quotation_to\", \"party_name\", \"customer_name\", \"column_break_7\", \"transaction_date\", \"valid_till\", \"custom_opportunity_from\", \"custom_deal_type\", \"custom_contract_expiry\", \"custom_pricing_model\", \"custom_discount_type\", \"column_break1\", \"order_type\", \"company\", \"has_unit_price_items\", \"amended_from\", \"custom_invoice_days\", \"custom_payment_terms\", \"invoicing_frequency\", \"invoicing_type\", \"currency_and_price_list\", \"currency\", \"conversion_rate\", \"column_break2\", \"selling_price_list\", \"price_list_currency\", \"plc_conversion_rate\", \"ignore_pricing_rule\", \"items_section\", \"scan_barcode\", \"last_scanned_warehouse\", \"items\", \"sec_break23\", \"total_qty\", \"total_net_weight\", \"column_break_28\", \"base_total\", \"base_net_total\", \"column_break_31\", \"total\", \"net_total\", \"taxes_section\", \"tax_category\", \"taxes_and_charges\", \"column_break_36\", \"shipping_rule\", \"column_break_34\", \"incoterm\", \"named_place\", \"section_break_36\", \"taxes\", \"section_break_39\", \"base_total_taxes_and_charges\", \"column_break_42\", \"total_taxes_and_charges\", \"totals\", \"base_grand_total\", \"base_rounding_adjustment\", \"base_rounded_total\", \"base_in_words\", \"column_break3\", \"grand_total\", \"rounding_adjustment\", \"rounded_total\", \"disable_rounded_total\", \"in_words\", \"section_break_44\", \"apply_discount_on\", \"base_discount_amount\", \"coupon_code\", \"column_break_46\", \"additional_discount_percentage\", \"discount_amount\", \"referral_sales_partner\", \"sec_tax_breakup\", \"other_charges_calculation\", \"bundle_items_section\", \"packed_items\", \"pricing_rule_details\", \"pricing_rules\", \"address_and_contact_tab\", \"billing_address_section\", \"customer_address\", \"address_display\", \"col_break98\", \"contact_person\", \"contact_display\", \"contact_mobile\", \"contact_email\", \"shipping_address_section\", \"shipping_address_name\", \"column_break_81\", \"shipping_address\", \"company_address_section\", \"company_address\", \"column_break_87\", \"company_contact_person\", \"company_address_display\", \"terms_tab\", \"payment_schedule_section\", \"payment_terms_template\", \"payment_schedule\", \"terms_section_break\", \"tc_name\", \"terms\", \"more_info_tab\", \"subscription_section\", \"auto_repeat\", \"update_auto_repeat_reference\", \"print_settings\", \"letter_head\", \"group_same_items\", \"column_break_73\", \"select_print_heading\", \"language\", \"lost_reasons_section\", \"lost_reasons\", \"competitors\", \"column_break_117\", \"order_lost_reason\", \"additional_info_section\", \"status\", \"customer_group\", \"territory\", \"column_break_108\", \"campaign\", \"source\", \"column_break4\", \"opportunity\", \"supplier_quotation\", \"enq_det\", \"connections_tab\"]"
 },
 {
  "default_value": null,
  "doc_type": "Customer",
  "docstatus": 0,
  "doctype": "Property Setter",
  "doctype_or_field": "DocType",
  "field_name": null,
  "is_system_generated": 0,
  "modified": "2026-06-05 13:13:14.987642",
  "module": null,
  "name": "Customer-main-field_order",
  "property": "field_order",
  "property_type": "Data",
  "row_name": null,
  "value": "[\"basic_info\", \"naming_series\", \"salutation\", \"custom_transaction_type\", \"customer_name\", \"customer_name_in_arabic\", \"customer_type\", \"customer_group\", \"custom_source_of_creation\", \"custom_organization_id\", \"custom_belong_to\", \"column_break0\", \"territory\", \"gender\", \"lead_name\", \"opportunity_name\", \"prospect_name\", \"custom_sales_person\", \"account_manager\", \"image\", \"custom_vat_certificate\", \"custom_trade_license\", \"defaults_tab\", \"default_currency\", \"default_bank_account\", \"column_break_14\", \"default_price_list\", \"internal_customer_section\", \"is_internal_customer\", \"represents_company\", \"column_break_70\", \"companies\", \"more_info\", \"market_segment\", \"industry\", \"customer_pos_id\", \"website\", \"language\", \"column_break_45\", \"customer_details\", \"dashboard_tab\", \"contact_and_address_tab\", \"address_contacts\", \"address_html\", \"column_break1\", \"contact_html\", \"primary_address_and_contact_detail\", \"column_break_26\", \"customer_primary_address\", \"primary_address\", \"column_break_nwor\", \"customer_primary_contact\", \"mobile_no\", \"email_id\", \"first_name\", \"last_name\", \"custom_poc_section\", \"custom_poc\", \"tax_tab\", \"taxation_section\", \"tax_id\", \"column_break_21\", \"tax_category\", \"tax_withholding_category\", \"accounting_tab\", \"credit_limit_section\", \"payment_terms\", \"credit_limits\", \"default_receivable_accounts\", \"accounts\", \"loyalty_points_tab\", \"loyalty_program\", \"column_break_54\", \"loyalty_program_tier\", \"sales_team_tab\", \"sales_team\", \"sales_team_section\", \"default_sales_partner\", \"column_break_66\", \"default_commission_rate\", \"settings_tab\", \"so_required\", \"dn_required\", \"column_break_53\", \"is_frozen\", \"disabled\", \"portal_users_tab\", \"portal_users\"]"
 }
]
